qsm/__init__.py
qsm/gate.py
qsm/method.py
qsm/qubit.py
qsm/core/__init__.py
qsm/core/amplitude.py
qsm/core/gen_qubit.py
qsm/core/mesure.py
qsm/core/phaseangle.py
qsm/core/probabilities.py
qsm-0.1.0.dist-info/METADATA
qsm-0.1.0.dist-info/WHEEL
qsm-0.1.0.dist-info/top_level.txt
qsm-0.1.0.dist-info/RECORD
