Metadata-Version: 2.1
Name: qsm
Version: 0.1.0
Requires-Dist: numpy
Requires-Dist: scipy
